push_notification/__init__.py
push_notification/settings.py
push_notification/urls.py
push_notification/event/__init__.py
push_notification/event/admin.py
push_notification/event/apps.py
push_notification/event/interfaces.py
push_notification/event/models.py
push_notification/event/serializers.py
push_notification/event/tests.py
push_notification/event/views.py
push_notification/event/management/__init__.py
push_notification/event/management/commands/__init__.py
push_notification/event/management/commands/push_notifications_emitter.py
push_notification/event/migrations/0001_initial.py
push_notification/event/migrations/0002_auto_20200403_1401.py
push_notification/event/migrations/0003_use_model_JSONField.py
push_notification/event/migrations/__init__.py
spotii_push_notification2-1.1.4.dist-info/METADATA
spotii_push_notification2-1.1.4.dist-info/WHEEL
spotii_push_notification2-1.1.4.dist-info/top_level.txt
spotii_push_notification2-1.1.4.dist-info/RECORD
