Metadata-Version: 2.1
Name: spotii-push-notification2
Version: 1.1.4
Summary: Spotii Push Notification
Home-page: 
Author-email: hello@nuclearo.com
Keywords: Spotii,Push Notification
Requires-Dist: aiohttp
Requires-Dist: django
Requires-Dist: djangorestframework
Requires-Dist: asgiref
